asciigenator/__init__.py
asciigenator/cli.py
asciigenator/core.py
asciigenator-0.0.6.dist-info/licenses/LICENSE
asciigenator-0.0.6.dist-info/METADATA
asciigenator-0.0.6.dist-info/WHEEL
asciigenator-0.0.6.dist-info/entry_points.txt
asciigenator-0.0.6.dist-info/top_level.txt
asciigenator-0.0.6.dist-info/RECORD
